blank/__init__.py
blank/blank_func.py
blank/main.py
blank-0.1.0.dist-info/LICENSE
blank-0.1.0.dist-info/METADATA
blank-0.1.0.dist-info/WHEEL
blank-0.1.0.dist-info/entry_points.txt
blank-0.1.0.dist-info/top_level.txt
blank-0.1.0.dist-info/RECORD
